soda_nginx/main.py
soda_nginx/run_nginx.py
soda_nginx_bin/nginx.exe
soda_nginx_bin/nginx.zip
soda_nginx_bin/conf/fastcgi.conf
soda_nginx_bin/conf/fastcgi_params
soda_nginx_bin/conf/koi-utf
soda_nginx_bin/conf/koi-win
soda_nginx_bin/conf/mime.types
soda_nginx_bin/conf/nginx.conf
soda_nginx_bin/conf/scgi_params
soda_nginx_bin/conf/uwsgi_params
soda_nginx_bin/conf/win-utf
soda_nginx_bin/contrib/README
soda_nginx_bin/contrib/geo2nginx.pl
soda_nginx_bin/contrib/unicode2nginx/koi-utf
soda_nginx_bin/contrib/unicode2nginx/unicode-to-nginx.pl
soda_nginx_bin/contrib/unicode2nginx/win-utf
soda_nginx_bin/contrib/vim/ftdetect/nginx.vim
soda_nginx_bin/contrib/vim/ftplugin/nginx.vim
soda_nginx_bin/contrib/vim/indent/nginx.vim
soda_nginx_bin/contrib/vim/syntax/nginx.vim
soda_nginx_bin/docs/CHANGES
soda_nginx_bin/docs/CHANGES.ru
soda_nginx_bin/docs/CODE_OF_CONDUCT.md
soda_nginx_bin/docs/CONTRIBUTING.md
soda_nginx_bin/docs/LICENSE
soda_nginx_bin/docs/OpenSSL.LICENSE
soda_nginx_bin/docs/PCRE.LICENCE
soda_nginx_bin/docs/README.md
soda_nginx_bin/docs/SECURITY.md
soda_nginx_bin/docs/zlib.LICENSE
soda_nginx_bin/html/50x.html
soda_nginx_bin/html/index.html
soda_nginx-2025.5.13.5.dist-info/METADATA
soda_nginx-2025.5.13.5.dist-info/WHEEL
soda_nginx-2025.5.13.5.dist-info/entry_points.txt
soda_nginx-2025.5.13.5.dist-info/licenses/LICENSE
soda_nginx-2025.5.13.5.dist-info/RECORD
