Metadata-Version: 2.4
Name: soda-nginx
Version: 2025.5.13.5
Summary: dev nginx server via pip (Windows only)
Project-URL: Repository, https://github.com/soda92/soda-nginx
License-File: LICENSE
Requires-Python: >=3.11
Requires-Dist: sodatools>=2025.2.16.0
